{"armature":[{"ik":[],"type":"MovieClip","name":"MovieClip","skin":[{"name":"","slot":[{"display":[{"path":"nn_ghgh11","type":"image","name":"nn_ghgh11","transform":{}}],"blendMode":"add","name":"nn_ghgh111"},{"display":[{"path":"nn_ghgh11","type":"image","name":"nn_ghgh11","transform":{}}],"blendMode":"add","name":"nn_ghgh11"},{"display":[{"path":"nn-zhou","type":"image","name":"nn-zhou","transform":{}}],"blendMode":"add","name":"nn-zhou"},{"display":[{"path":"nn-guang","type":"image","name":"nn-guang","transform":{}}],"name":"nn-guang"},{"display":[{"path":"jjh_nn_sl_cd3","type":"image","name":"jjh_nn_sl_cd3","transform":{}}],"name":"jjh_nn_sl_cd3"},{"display":[{"path":"jjh_nn_sl_cd","type":"image","name":"jjh_nn_sl_cd","transform":{}},{"path":"jjh_nn_sl_cd","type":"image","name":"jjh_nn_sl_cd","transform":{}},{"path":"jjh_nn_sl_cd","type":"image","name":"jjh_nn_sl_cd","transform":{}}],"name":"newLayer9"},{"display":[{"path":"jjh_nn_sl_cd3","type":"image","name":"jjh_nn_sl_cd3","transform":{}},{"path":"jjh_nn_sl_cd3","type":"image","name":"jjh_nn_sl_cd3","transform":{}},{"path":"jjh_nn_sl_cd3","type":"image","name":"jjh_nn_sl_cd3","transform":{}}],"name":"newLayer12"},{"display":[{"path":"BaiRenWin","type":"image","name":"BaiRenWin","transform":{}}],"blendMode":"add","name":"BaiRenWin"},{"display":[{"path":"nn-走灯","type":"image","name":"nn-走灯","transform":{}}],"blendMode":"add","name":"nn-走灯"},{"display":[{"path":"nn_gg1","type":"image","name":"nn_gg1","transform":{}}],"blendMode":"add","name":"nn_gg1"},{"display":[{"path":"BaiRenWin","type":"image","name":"BaiRenWin","transform":{}},{"path":"BaiRenWin","type":"image","name":"BaiRenWin","transform":{}},{"path":"BaiRenWin","type":"image","name":"BaiRenWin","transform":{}}],"blendMode":"add","name":"newLayer6"},{"display":[{"path":"nn_gg7","type":"image","name":"nn_gg7","transform":{}}],"blendMode":"add","name":"nn_gg7"},{"display":[{"path":"BaiRenWin","type":"image","name":"BaiRenWin","transform":{}},{"path":"BaiRenWin","type":"image","name":"BaiRenWin","transform":{}},{"path":"BaiRenWin","type":"image","name":"BaiRenWin","transform":{}}],"blendMode":"add","name":"newLayer5"},{"display":[{"path":"jjh_nn_sl_cd1","type":"image","name":"jjh_nn_sl_cd1","transform":{}},{"path":"jjh_nn_sl_cd1","type":"image","name":"jjh_nn_sl_cd1","transform":{}},{"path":"jjh_nn_sl_cd1","type":"image","name":"jjh_nn_sl_cd1","transform":{}}],"name":"newLayer10"},{"display":[{"path":"jjh_nn_sl_cd4","type":"image","name":"jjh_nn_sl_cd4","transform":{}}],"name":"jjh_nn_sl_cd4"},{"display":[{"path":"nn-指针","type":"image","name":"nn-指针","transform":{}}],"name":"nn-指针"},{"display":[{"path":"nn-guang","type":"image","name":"nn-guang","transform":{}},{"path":"nn-guang","type":"image","name":"nn-guang","transform":{}},{"path":"nn-guang","type":"image","name":"nn-guang","transform":{}}],"name":"newLayer2"},{"display":[{"path":"nn_gg7","type":"image","name":"nn_gg7","transform":{}},{"path":"nn_gg7","type":"image","name":"nn_gg7","transform":{}},{"path":"nn_gg7","type":"image","name":"nn_gg7","transform":{}}],"blendMode":"add","name":"newLayer"},{"display":[{"path":"nn_gg7","type":"image","name":"nn_gg7","transform":{}}],"blendMode":"add","name":"nn_gg71"},{"display":[{"path":"BaiRenWin","type":"image","name":"BaiRenWin","transform":{}},{"path":"BaiRenWin","type":"image","name":"BaiRenWin","transform":{}},{"path":"BaiRenWin","type":"image","name":"BaiRenWin","transform":{}}],"blendMode":"add","name":"newLayer4"},{"display":[{"path":"nn_gg2","type":"image","name":"nn_gg2","transform":{}}],"blendMode":"add","name":"nn_gg2"},{"display":[{"path":"jjh_nn_sl_cd1","type":"image","name":"jjh_nn_sl_cd1","transform":{}},{"path":"jjh_nn_sl_cd1","type":"image","name":"jjh_nn_sl_cd1","transform":{}},{"path":"jjh_nn_sl_cd1","type":"image","name":"jjh_nn_sl_cd1","transform":{}}],"name":"newLayer8"},{"display":[{"path":"jjh_nn_sl_cd2","type":"image","name":"jjh_nn_sl_cd2","transform":{}}],"name":"jjh_nn_sl_cd2"},{"display":[{"path":"jjh_nn_sl_cd4","type":"image","name":"jjh_nn_sl_cd4","transform":{}}],"name":"jjh_nn_sl_cd41"},{"display":[{"path":"jjh_nn_sl_cd1","type":"image","name":"jjh_nn_sl_cd1","transform":{}}],"name":"jjh_nn_sl_cd1"},{"display":[{"path":"nn_pmd","type":"image","name":"nn_pmd","transform":{}},{"path":"nn_pmd1","type":"image","name":"nn_pmd1","transform":{}}],"name":"nn_pmd"},{"display":[{"path":"nn_gg1","type":"image","name":"nn_gg1","transform":{}},{"path":"nn_gg1","type":"image","name":"nn_gg1","transform":{}},{"path":"nn_gg1","type":"image","name":"nn_gg1","transform":{}}],"blendMode":"add","name":"newLayer1"},{"display":[{"path":"未标题-2","type":"image","name":"未标题-2","transform":{}}],"name":"未标题-2"},{"display":[{"path":"sss_flah_room_shengli_guang","type":"image","name":"sss_flah_room_shengli_guang","transform":{}}],"blendMode":"add","name":"sss_flah_room_shengli_guang"},{"display":[{"path":"jjh_nn_sl_cd2","type":"image","name":"jjh_nn_sl_cd2","transform":{}},{"path":"jjh_nn_sl_cd2","type":"image","name":"jjh_nn_sl_cd2","transform":{}},{"path":"jjh_nn_sl_cd2","type":"image","name":"jjh_nn_sl_cd2","transform":{}}],"name":"newLayer11"},{"display":[{"path":"nn-zhou","type":"image","name":"nn-zhou","transform":{}}],"name":"nn-zhou1"},{"display":[{"path":"jjh_nn_sl_cd","type":"image","name":"jjh_nn_sl_cd","transform":{}}],"name":"jjh_nn_sl_cd"},{"display":[{"path":"BaiRenWin","type":"image","name":"BaiRenWin","transform":{}},{"path":"BaiRenWin","type":"image","name":"BaiRenWin","transform":{}},{"path":"BaiRenWin","type":"image","name":"BaiRenWin","transform":{}}],"name":"newLayer7"}]}],"aabb":{"width":908,"y":-442.4969399664791,"height":908,"x":-444.43601507588534},"slot":[{"blendMode":"add","parent":"nn_gg7","displayIndex":-1,"name":"nn_gg7","color":{}},{"blendMode":"add","z":1,"parent":"nn_gg71","displayIndex":-1,"name":"nn_gg71","color":{}},{"blendMode":"add","z":2,"parent":"newLayer1","displayIndex":-1,"name":"newLayer1","color":{}},{"blendMode":"add","z":3,"parent":"newLayer","displayIndex":-1,"name":"newLayer","color":{}},{"blendMode":"add","z":4,"parent":"nn_gg1","displayIndex":-1,"name":"nn_gg1","color":{}},{"blendMode":"add","z":5,"parent":"nn-zhou","displayIndex":-1,"name":"nn-zhou","color":{}},{"z":6,"displayIndex":-1,"name":"nn-zhou1","parent":"nn-zhou1","color":{}},{"z":7,"displayIndex":-1,"name":"nn_pmd","parent":"nn_pmd","color":{}},{"blendMode":"add","z":8,"parent":"nn-走灯","displayIndex":-1,"name":"nn-走灯","color":{}},{"z":9,"displayIndex":-1,"name":"nn-指针","parent":"nn-指针","color":{}},{"blendMode":"add","z":10,"parent":"sss_flah_room_shengli_guang","displayIndex":-1,"name":"sss_flah_room_shengli_guang","color":{}},{"z":11,"displayIndex":-1,"name":"未标题-2","parent":"未标题-2","color":{}},{"blendMode":"add","z":12,"parent":"nn_gg2","displayIndex":-1,"name":"nn_gg2","color":{}},{"z":13,"displayIndex":-1,"name":"nn-guang","parent":"nn-guang","color":{}},{"z":14,"displayIndex":-1,"name":"newLayer2","parent":"newLayer2","color":{}},{"blendMode":"add","z":15,"parent":"nn_ghgh11","displayIndex":-1,"name":"nn_ghgh11","color":{}},{"blendMode":"add","z":16,"parent":"nn_ghgh111","displayIndex":-1,"name":"nn_ghgh111","color":{}},{"z":17,"displayIndex":-1,"name":"newLayer3","parent":"newLayer3","color":{}},{"blendMode":"add","z":18,"parent":"BaiRenWin","displayIndex":-1,"name":"BaiRenWin","color":{}},{"blendMode":"add","z":19,"parent":"newLayer4","displayIndex":-1,"name":"newLayer4","color":{}},{"blendMode":"add","z":20,"parent":"newLayer5","displayIndex":-1,"name":"newLayer5","color":{}},{"blendMode":"add","z":21,"parent":"newLayer6","displayIndex":-1,"name":"newLayer6","color":{}},{"z":22,"displayIndex":-1,"name":"newLayer7","parent":"newLayer7","color":{}},{"z":23,"displayIndex":-1,"name":"jjh_nn_sl_cd","parent":"jjh_nn_sl_cd","color":{}},{"z":24,"displayIndex":-1,"name":"jjh_nn_sl_cd1","parent":"jjh_nn_sl_cd1","color":{}},{"z":25,"displayIndex":-1,"name":"newLayer8","parent":"newLayer8","color":{}},{"z":26,"displayIndex":-1,"name":"newLayer9","parent":"newLayer9","color":{}},{"z":27,"displayIndex":-1,"name":"newLayer10","parent":"newLayer10","color":{}},{"z":28,"displayIndex":-1,"name":"jjh_nn_sl_cd2","parent":"jjh_nn_sl_cd2","color":{}},{"z":29,"displayIndex":-1,"name":"newLayer11","parent":"newLayer11","color":{}},{"z":30,"displayIndex":-1,"name":"jjh_nn_sl_cd3","parent":"jjh_nn_sl_cd3","color":{}},{"z":31,"displayIndex":-1,"name":"newLayer12","parent":"newLayer12","color":{}},{"z":32,"displayIndex":-1,"name":"jjh_nn_sl_cd4","parent":"jjh_nn_sl_cd4","color":{}},{"z":33,"displayIndex":-1,"name":"jjh_nn_sl_cd41","parent":"jjh_nn_sl_cd41","color":{}}],"animation":[{"frame":[],"ffd":[],"playTimes":0,"duration":121,"slot":[{"frame":[{"displayIndex":-1,"tweenEasing":null,"duration":73},{"tweenEasing":0,"color":{"aM":0},"duration":5},{"tweenEasing":0,"duration":12},{"tweenEasing":null,"color":{"aM":0},"duration":31}],"name":"nn_gg7"},{"frame":[{"displayIndex":-1,"tweenEasing":null,"duration":74},{"tweenEasing":0,"color":{"aM":0},"duration":5},{"tweenEasing":0,"duration":13},{"tweenEasing":null,"color":{"aM":0},"duration":29}],"name":"nn_gg1"},{"frame":[{"displayIndex":-1,"tweenEasing":null,"duration":74},{"tweenEasing":0,"color":{"aM":0},"duration":5},{"tweenEasing":0,"duration":11},{"tweenEasing":null,"color":{"aM":0},"duration":31}],"name":"nn_gg71"},{"frame":[{"displayIndex":-1,"tweenEasing":null,"duration":93},{"tweenEasing":null,"duration":4},{"displayIndex":1,"tweenEasing":null,"duration":4},{"tweenEasing":null,"duration":4},{"displayIndex":1,"tweenEasing":null,"duration":4},{"tweenEasing":null,"duration":4},{"displayIndex":1,"tweenEasing":null,"duration":4},{"tweenEasing":null,"duration":4},{"displayIndex":1,"tweenEasing":null,"duration":0}],"name":"nn_pmd"},{"frame":[{"displayIndex":-1,"tweenEasing":null,"duration":76},{"tweenEasing":0,"color":{"aM":27},"duration":3},{"tweenEasing":0,"color":{"aM":27},"duration":4},{"tweenEasing":0,"color":{"aM":27},"duration":4},{"tweenEasing":0,"color":{"aM":20},"duration":5},{"tweenEasing":0,"color":{"aM":30},"duration":5},{"tweenEasing":0,"duration":5},{"tweenEasing":0,"color":{"aM":0},"duration":5},{"tweenEasing":0,"duration":6},{"tweenEasing":null,"color":{"aM":0},"duration":8}],"name":"nn-zhou"},{"frame":[{"displayIndex":-1,"tweenEasing":null,"duration":76},{"tweenEasing":0,"color":{"aM":27},"duration":3},{"tweenEasing":0,"color":{"aM":27},"duration":4},{"tweenEasing":0,"color":{"aM":27},"duration":4},{"tweenEasing":0,"color":{"aM":20},"duration":5},{"tweenEasing":0,"color":{"aM":30},"duration":5},{"tweenEasing":0,"duration":5},{"tweenEasing":0,"color":{"aM":0},"duration":5},{"tweenEasing":0,"duration":6},{"tweenEasing":null,"color":{"aM":0},"duration":8}],"name":"nn-zhou1"},{"frame":[{"displayIndex":-1,"tweenEasing":null,"duration":77},{"tweenEasing":0,"color":{"aM":0},"duration":5},{"displayIndex":1,"tweenEasing":0,"color":{"aM":30},"duration":13},{"displayIndex":2,"tweenEasing":null,"color":{"aM":0},"duration":26}],"name":"newLayer"},{"frame":[{"displayIndex":-1,"tweenEasing":null,"duration":76},{"tweenEasing":0,"color":{"aM":0},"duration":5},{"displayIndex":1,"tweenEasing":0,"color":{"aM":27},"duration":13},{"displayIndex":2,"tweenEasing":null,"color":{"aM":0},"duration":27}],"name":"newLayer1"},{"frame":[{"tweenEasing":0,"color":{"aM":85},"duration":10},{"tweenEasing":0,"color":{"aM":80},"duration":7},{"tweenEasing":0,"color":{"aM":80},"duration":8},{"tweenEasing":0,"color":{"aM":80},"duration":6},{"tweenEasing":0,"color":{"aM":80},"duration":6},{"tweenEasing":0,"color":{"aM":80},"duration":5},{"tweenEasing":0,"color":{"aM":80},"duration":6},{"tweenEasing":0,"color":{"aM":80},"duration":5},{"tweenEasing":0,"color":{"aM":80},"duration":9},{"tweenEasing":0,"color":{"aM":80},"duration":15},{"tweenEasing":0,"color":{"aM":80},"duration":7},{"tweenEasing":0,"color":{"aM":80},"duration":14},{"tweenEasing":null,"color":{"aM":23},"duration":23}],"name":"nn-走灯"},{"frame":[{"tweenEasing":0,"duration":10},{"tweenEasing":0,"duration":3},{"tweenEasing":0,"duration":4},{"tweenEasing":0,"duration":8},{"tweenEasing":0,"duration":3},{"tweenEasing":0,"duration":3},{"tweenEasing":0,"duration":6},{"tweenEasing":0,"duration":2},{"tweenEasing":0,"duration":3},{"tweenEasing":0,"duration":6},{"tweenEasing":0,"duration":3},{"tweenEasing":0,"duration":2},{"tweenEasing":0,"duration":4},{"tweenEasing":0,"duration":5},{"tweenEasing":0,"duration":6},{"tweenEasing":0,"duration":9},{"tweenEasing":null,"duration":44}],"name":"nn-指针"}],"name":"nn_mlzpan","bone":[{"frame":[{"tweenEasing":null,"transform":{},"duration":121}],"name":"root"},{"frame":[{"tweenEasing":null,"transform":{},"duration":73},{"tweenEasing":0,"transform":{"scX":0.4,"scY":0.4},"duration":5},{"tweenEasing":0,"transform":{"scX":0.6,"scY":0.6},"duration":12},{"tweenEasing":null,"transform":{"scX":1.5,"scY":1.5},"duration":31}],"name":"nn_gg7"},{"frame":[{"tweenEasing":null,"transform":{},"duration":74},{"tweenEasing":0,"transform":{"scX":0.6,"scY":0.6},"duration":5},{"tweenEasing":0,"transform":{"scX":0.8,"scY":0.8},"duration":13},{"tweenEasing":null,"transform":{"scX":2.5,"scY":2.5},"duration":29}],"name":"nn_gg1"},{"frame":[{"tweenEasing":null,"transform":{},"duration":74},{"tweenEasing":0,"transform":{"scX":0.4,"scY":0.4},"duration":5},{"tweenEasing":0,"transform":{"scX":0.6,"scY":0.6},"duration":11},{"tweenEasing":null,"transform":{"scX":1.5,"scY":1.5},"duration":31}],"name":"nn_gg71"},{"frame":[{"tweenEasing":null,"transform":{},"duration":93},{"tweenEasing":null,"transform":{"y":187.012,"skX":-45.53,"skY":-45.53,"x":-174.1293},"duration":4},{"tweenEasing":null,"transform":{"y":190.9781,"skX":-45.53,"skY":-45.53,"x":-175.765},"duration":4},{"tweenEasing":null,"transform":{"y":187.012,"skX":-45.53,"skY":-45.53,"x":-174.1293},"duration":4},{"tweenEasing":null,"transform":{"y":190.9781,"skX":-45.53,"skY":-45.53,"x":-175.765},"duration":4},{"tweenEasing":null,"transform":{"y":187.012,"skX":-45.53,"skY":-45.53,"x":-174.1293},"duration":4},{"tweenEasing":null,"transform":{"y":190.9781,"skX":-45.53,"skY":-45.53,"x":-175.765},"duration":4},{"tweenEasing":null,"transform":{"y":187.012,"skX":-45.53,"skY":-45.53,"x":-174.1293},"duration":4},{"tweenEasing":null,"transform":{"y":190.9781,"skX":-45.53,"skY":-45.53,"x":-175.765},"duration":0}],"name":"nn_pmd"},{"frame":[{"tweenEasing":null,"transform":{},"duration":76},{"tweenEasing":0,"transform":{"y":-152.5927,"skX":-45.49,"skY":-45.49,"x":163.455},"duration":3},{"tweenEasing":0,"transform":{"y":-209.1855,"skX":-91,"skY":-91,"x":4.1294},"duration":4},{"tweenEasing":0,"transform":{"y":-144.2533,"skX":-135,"skY":-135,"x":-145.7012},"duration":4},{"tweenEasing":0,"transform":{"y":5.4687,"skX":180,"skY":180,"x":-205.1586},"duration":5},{"tweenEasing":0,"transform":{"y":160.8168,"skX":134,"skY":134,"x":-148.8978},"duration":5},{"tweenEasing":0,"transform":{"y":160.8168,"skX":134,"skY":134,"x":-148.8978},"duration":5},{"tweenEasing":0,"transform":{"y":160.8168,"skX":134,"skY":134,"x":-148.8978},"duration":5},{"tweenEasing":0,"transform":{"y":160.8168,"skX":134,"skY":134,"x":-148.8978},"duration":6},{"tweenEasing":null,"transform":{"y":160.8168,"skX":134,"skY":134,"x":-148.8978},"duration":8}],"name":"nn-zhou"},{"frame":[{"tweenEasing":null,"transform":{},"duration":76},{"tweenEasing":0,"transform":{"y":-152.5927,"skX":-45.49,"skY":-45.49,"x":163.455},"duration":3},{"tweenEasing":0,"transform":{"y":8.4681,"skX":-1.6031,"skY":-1.6031,"x":227.4313},"duration":4},{"tweenEasing":0,"transform":{"y":147.8181,"skX":45,"skY":45,"x":148.5448},"duration":4},{"tweenEasing":0,"transform":{"y":226.2223,"skX":90,"skY":90,"x":8.7955},"duration":5},{"tweenEasing":0,"transform":{"y":160.8168,"skX":134,"skY":134,"x":-148.8978},"duration":5},{"tweenEasing":0,"transform":{"y":160.8168,"skX":134,"skY":134,"x":-148.8978},"duration":5},{"tweenEasing":0,"transform":{"y":160.8168,"skX":134,"skY":134,"x":-148.8978},"duration":5},{"tweenEasing":0,"transform":{"y":160.8168,"skX":134,"skY":134,"x":-148.8978},"duration":6},{"tweenEasing":null,"transform":{"y":160.8168,"skX":134,"skY":134,"x":-148.8978},"duration":8}],"name":"nn-zhou1"},{"frame":[{"tweenEasing":null,"transform":{},"duration":77},{"tweenEasing":0,"transform":{"scX":0.4,"scY":0.4},"duration":5},{"tweenEasing":0,"transform":{"scX":0.6,"scY":0.6},"duration":13},{"tweenEasing":null,"transform":{"scX":1.5,"scY":1.5},"duration":26}],"name":"newLayer"},{"frame":[{"tweenEasing":null,"transform":{},"duration":76},{"tweenEasing":0,"transform":{"scX":0.6,"scY":0.6},"duration":5},{"tweenEasing":0,"transform":{"scX":0.8,"scY":0.8},"duration":13},{"tweenEasing":null,"transform":{"scX":2.5,"scY":2.5},"duration":27}],"name":"newLayer1"},{"frame":[{"tweenEasing":0,"transform":{"y":11.5031,"skX":91,"skY":91,"scY":-1,"x":9.564},"duration":10},{"tweenEasing":0,"transform":{"y":11.5031,"skX":-90,"skY":-90,"scY":-1,"x":9.564},"duration":7},{"tweenEasing":0,"transform":{"y":11.5031,"skX":90,"skY":90,"scY":-1,"x":9.564},"duration":8},{"tweenEasing":0,"transform":{"y":11.5031,"skX":-90,"skY":-90,"scY":-1,"x":9.564},"duration":6},{"tweenEasing":0,"transform":{"y":11.5031,"skX":90,"skY":90,"scY":-1,"x":9.564},"duration":6},{"tweenEasing":0,"transform":{"y":11.5031,"skX":-91,"skY":-91,"scY":-1,"x":9.564},"duration":5},{"tweenEasing":0,"transform":{"y":11.5031,"skX":88,"skY":88,"scY":-1,"x":9.564},"duration":6},{"tweenEasing":0,"transform":{"y":11.5031,"skX":-93,"skY":-93,"scY":-1,"x":9.564},"duration":5},{"tweenEasing":0,"transform":{"y":11.5031,"skX":87,"skY":87,"scY":-1,"x":9.564},"duration":9},{"tweenEasing":0,"transform":{"y":11.5031,"skX":-93,"skY":-93,"scY":-1,"x":9.564},"duration":15},{"tweenEasing":0,"transform":{"y":11.5031,"skX":47,"skY":47,"scY":-1,"x":9.564},"duration":7},{"tweenEasing":0,"transform":{"y":11.5031,"skX":47,"skY":47,"scY":-1,"x":9.564},"duration":14},{"tweenEasing":null,"transform":{"y":11.5031,"skX":47,"skY":47,"scY":-1,"x":9.564},"duration":23}],"name":"nn-走灯"},{"frame":[{"tweenEasing":0,"transform":{"y":9.1885,"skX":180,"skY":180,"x":4.07},"duration":10},{"tweenEasing":0,"transform":{"y":9.19,"x":4.07},"duration":3},{"tweenEasing":0,"transform":{"y":0.869,"skX":90,"skY":90,"x":4.07},"duration":4},{"tweenEasing":0,"transform":{"y":9.19,"skX":180,"skY":180,"x":4.07},"duration":8},{"tweenEasing":0,"transform":{"y":9.19,"x":1.8006},"duration":3},{"tweenEasing":0,"transform":{"y":-1.3625,"skX":90,"skY":90,"x":2.9353},"duration":3},{"tweenEasing":0,"transform":{"y":9.19,"skX":180,"skY":180,"x":4.07},"duration":6},{"tweenEasing":0,"transform":{"y":9.19,"x":4.07},"duration":2},{"tweenEasing":0,"transform":{"y":0.1126,"skX":72,"skY":72,"x":1.8006},"duration":3},{"tweenEasing":0,"transform":{"y":9.19,"skX":180,"skY":180,"x":4.07},"duration":6},{"tweenEasing":0,"transform":{"y":9.19,"x":4.07},"duration":3},{"tweenEasing":0,"transform":{"y":4.5378,"skX":81.8182,"skY":81.8182,"x":-5.5369},"duration":2},{"tweenEasing":0,"transform":{"y":9.19,"skX":180,"skY":180,"x":4.07},"duration":4},{"tweenEasing":0,"transform":{"y":3.1979,"skX":-96.9231,"skY":-96.9231,"x":4.0703},"duration":5},{"tweenEasing":0,"transform":{"y":7.68,"x":4.0706},"duration":6},{"tweenEasing":0,"transform":{"y":1.7402,"skX":77.0625,"skY":77.0625,"x":1.0445},"duration":9},{"tweenEasing":null,"transform":{"y":7.6771,"skX":137,"skY":137,"x":4.07},"duration":44}],"name":"nn-指针"},{"frame":[{"tweenEasing":null,"transform":{},"duration":121}],"name":"未标题-2"},{"frame":[{"tweenEasing":null,"transform":{},"duration":121}],"name":"sss_flah_room_shengli_guang"},{"frame":[{"tweenEasing":null,"transform":{},"duration":121}],"name":"nn_gg2"},{"frame":[{"tweenEasing":null,"transform":{},"duration":121}],"name":"nn-guang"},{"frame":[{"tweenEasing":null,"transform":{},"duration":121}],"name":"newLayer2"},{"frame":[{"tweenEasing":null,"transform":{},"duration":121}],"name":"nn_ghgh11"},{"frame":[{"tweenEasing":null,"transform":{},"duration":121}],"name":"nn_ghgh111"},{"frame":[{"tweenEasing":null,"transform":{},"duration":121}],"name":"newLayer3"},{"frame":[{"tweenEasing":null,"transform":{},"duration":121}],"name":"BaiRenWin"},{"frame":[{"tweenEasing":null,"transform":{},"duration":121}],"name":"newLayer4"},{"frame":[{"tweenEasing":null,"transform":{},"duration":121}],"name":"newLayer5"},{"frame":[{"tweenEasing":null,"transform":{},"duration":121}],"name":"newLayer6"},{"frame":[{"tweenEasing":null,"transform":{},"duration":121}],"name":"newLayer7"},{"frame":[{"tweenEasing":null,"transform":{},"duration":121}],"name":"jjh_nn_sl_cd"},{"frame":[{"tweenEasing":null,"transform":{},"duration":121}],"name":"jjh_nn_sl_cd1"},{"frame":[{"tweenEasing":null,"transform":{},"duration":121}],"name":"newLayer8"},{"frame":[{"tweenEasing":null,"transform":{},"duration":121}],"name":"newLayer9"},{"frame":[{"tweenEasing":null,"transform":{},"duration":121}],"name":"newLayer10"},{"frame":[{"tweenEasing":null,"transform":{},"duration":121}],"name":"jjh_nn_sl_cd2"},{"frame":[{"tweenEasing":null,"transform":{},"duration":121}],"name":"newLayer11"},{"frame":[{"tweenEasing":null,"transform":{},"duration":121}],"name":"jjh_nn_sl_cd3"},{"frame":[{"tweenEasing":null,"transform":{},"duration":121}],"name":"newLayer12"},{"frame":[{"tweenEasing":null,"transform":{},"duration":121}],"name":"jjh_nn_sl_cd4"},{"frame":[{"tweenEasing":null,"transform":{},"duration":121}],"name":"jjh_nn_sl_cd41"}]},{"frame":[],"ffd":[],"playTimes":0,"duration":90,"slot":[{"frame":[{"tweenEasing":0,"duration":7},{"tweenEasing":0,"duration":4},{"tweenEasing":null,"duration":79},{"tweenEasing":null,"duration":0}],"name":"未标题-2"},{"frame":[{"tweenEasing":0,"duration":7},{"tweenEasing":0,"duration":4},{"tweenEasing":0,"duration":79},{"tweenEasing":null,"duration":0}],"name":"sss_flah_room_shengli_guang"},{"frame":[{"tweenEasing":0,"color":{"aM":40},"duration":5},{"tweenEasing":0,"duration":5},{"tweenEasing":null,"color":{"aM":0},"duration":80}],"name":"nn_gg2"},{"frame":[{"tweenEasing":0,"duration":3},{"tweenEasing":0,"duration":8},{"tweenEasing":null,"color":{"aM":0},"duration":79}],"name":"nn-guang"},{"frame":[{"displayIndex":-1,"tweenEasing":null,"duration":2},{"tweenEasing":0,"duration":3},{"displayIndex":1,"tweenEasing":0,"duration":8},{"displayIndex":2,"tweenEasing":null,"color":{"aM":0},"duration":77}],"name":"newLayer2"},{"frame":[{"displayIndex":-1,"tweenEasing":null,"duration":2},{"tweenEasing":0,"duration":5},{"tweenEasing":0,"duration":9},{"tweenEasing":null,"color":{"aM":0},"duration":74}],"name":"nn_ghgh11"},{"frame":[{"displayIndex":-1,"tweenEasing":null,"duration":2},{"tweenEasing":0,"duration":5},{"tweenEasing":0,"duration":9},{"tweenEasing":null,"color":{"aM":0},"duration":74}],"name":"nn_ghgh111"},{"frame":[{"displayIndex":-1,"tweenEasing":null,"duration":7},{"tweenEasing":0,"color":{"aM":17},"duration":24},{"tweenEasing":0,"duration":23},{"tweenEasing":null,"color":{"aM":15},"duration":36}],"name":"BaiRenWin"},{"frame":[{"displayIndex":-1,"tweenEasing":null,"duration":13},{"tweenEasing":0,"color":{"aM":17},"duration":24},{"displayIndex":1,"tweenEasing":0,"duration":23},{"displayIndex":2,"tweenEasing":null,"color":{"aM":15},"duration":30}],"name":"newLayer4"},{"frame":[{"displayIndex":-1,"tweenEasing":null,"duration":9},{"tweenEasing":0,"color":{"aM":17},"duration":24},{"displayIndex":1,"tweenEasing":0,"duration":23},{"displayIndex":2,"tweenEasing":null,"color":{"aM":15},"duration":34}],"name":"newLayer5"},{"frame":[{"displayIndex":-1,"tweenEasing":null,"duration":15},{"tweenEasing":0,"color":{"aM":17},"duration":24},{"displayIndex":1,"tweenEasing":0,"duration":23},{"displayIndex":2,"tweenEasing":null,"color":{"aM":15},"duration":28}],"name":"newLayer6"},{"frame":[{"displayIndex":-1,"tweenEasing":null,"duration":24},{"tweenEasing":0,"color":{"aM":17},"duration":24},{"displayIndex":1,"tweenEasing":0,"duration":23},{"displayIndex":2,"tweenEasing":null,"color":{"aM":15},"duration":19}],"name":"newLayer7"},{"frame":[{"displayIndex":-1,"tweenEasing":null,"duration":8},{"tweenEasing":0,"color":{"aM":0},"duration":3},{"tweenEasing":0,"duration":7},{"tweenEasing":null,"color":{"aM":0},"duration":72}],"name":"jjh_nn_sl_cd"},{"frame":[{"displayIndex":-1,"tweenEasing":null,"duration":8},{"tweenEasing":0,"color":{"aM":0},"duration":4},{"tweenEasing":0,"duration":7},{"tweenEasing":0,"color":{"aM":0},"duration":1},{"tweenEasing":null,"duration":70}],"name":"jjh_nn_sl_cd1"},{"frame":[{"displayIndex":-1,"tweenEasing":null,"duration":8},{"tweenEasing":0,"color":{"aM":0},"duration":4},{"displayIndex":1,"tweenEasing":0,"duration":7},{"displayIndex":2,"tweenEasing":null,"color":{"aM":0},"duration":71}],"name":"newLayer8"},{"frame":[{"displayIndex":-1,"tweenEasing":null,"duration":10},{"tweenEasing":0,"color":{"aM":0},"duration":3},{"displayIndex":1,"tweenEasing":0,"duration":7},{"displayIndex":2,"tweenEasing":null,"color":{"aM":0},"duration":70}],"name":"newLayer9"},{"frame":[{"displayIndex":-1,"tweenEasing":null,"duration":9},{"tweenEasing":0,"color":{"aM":0},"duration":4},{"displayIndex":1,"tweenEasing":0,"duration":7},{"displayIndex":2,"tweenEasing":null,"color":{"aM":0},"duration":70}],"name":"newLayer10"},{"frame":[{"displayIndex":-1,"tweenEasing":null,"duration":10},{"tweenEasing":0,"color":{"aM":0},"duration":4},{"tweenEasing":0,"duration":8},{"tweenEasing":null,"color":{"aM":0},"duration":68}],"name":"jjh_nn_sl_cd2"},{"frame":[{"displayIndex":-1,"tweenEasing":null,"duration":8},{"tweenEasing":0,"color":{"aM":0},"duration":3},{"displayIndex":1,"tweenEasing":0,"duration":9},{"displayIndex":2,"tweenEasing":null,"color":{"aM":0},"duration":70}],"name":"newLayer11"},{"frame":[{"displayIndex":-1,"tweenEasing":null,"duration":8},{"tweenEasing":0,"color":{"aM":0},"duration":4},{"tweenEasing":0,"duration":8},{"tweenEasing":null,"color":{"aM":0},"duration":70}],"name":"jjh_nn_sl_cd3"},{"frame":[{"displayIndex":-1,"tweenEasing":null,"duration":9},{"tweenEasing":0,"color":{"aM":0},"duration":4},{"displayIndex":1,"tweenEasing":0,"duration":8},{"displayIndex":2,"tweenEasing":null,"color":{"aM":0},"duration":69}],"name":"newLayer12"},{"frame":[{"displayIndex":-1,"tweenEasing":null,"duration":9},{"tweenEasing":0,"color":{"aM":0},"duration":5},{"tweenEasing":0,"duration":8},{"tweenEasing":null,"color":{"aM":0},"duration":68}],"name":"jjh_nn_sl_cd4"},{"frame":[{"displayIndex":-1,"tweenEasing":null,"duration":9},{"tweenEasing":0,"duration":6},{"tweenEasing":0,"duration":8},{"tweenEasing":null,"color":{"aM":0},"duration":67}],"name":"jjh_nn_sl_cd41"}],"name":"nn_mljiangli","bone":[{"frame":[{"tweenEasing":null,"transform":{},"duration":90}],"name":"root"},{"frame":[{"tweenEasing":null,"transform":{},"duration":90}],"name":"nn_gg7"},{"frame":[{"tweenEasing":null,"transform":{},"duration":90}],"name":"nn_gg1"},{"frame":[{"tweenEasing":null,"transform":{},"duration":90}],"name":"nn_gg71"},{"frame":[{"tweenEasing":null,"transform":{},"duration":90}],"name":"nn_pmd"},{"frame":[{"tweenEasing":null,"transform":{},"duration":90}],"name":"nn-zhou"},{"frame":[{"tweenEasing":null,"transform":{},"duration":90}],"name":"nn-zhou1"},{"frame":[{"tweenEasing":null,"transform":{},"duration":90}],"name":"newLayer"},{"frame":[{"tweenEasing":null,"transform":{},"duration":90}],"name":"newLayer1"},{"frame":[{"tweenEasing":null,"transform":{},"duration":90}],"name":"nn-走灯"},{"frame":[{"tweenEasing":null,"transform":{},"duration":90}],"name":"nn-指针"},{"frame":[{"tweenEasing":0,"transform":{"y":-1.867,"scX":0.01,"scY":0.01},"duration":7},{"tweenEasing":0,"transform":{"y":-151.2301,"scX":1.2,"scY":1.2,"x":11.669},"duration":4},{"tweenEasing":null,"transform":{"y":-151.2301,"x":11.669},"duration":79},{"tweenEasing":null,"transform":{"y":-151.2301,"x":11.669},"duration":0}],"name":"未标题-2"},{"frame":[{"tweenEasing":0,"transform":{"y":0.0583,"skX":-3.3371,"skY":-3.3371,"scX":0.01,"scY":0.01,"x":-5.8278},"duration":7},{"tweenEasing":0,"transform":{"y":-326.6733,"scX":1.2,"scY":1.2,"x":-45.5024},"duration":4},{"tweenEasing":0,"transform":{"y":-326.6733,"x":-45.5024},"duration":79},{"tweenEasing":null,"transform":{"y":-326.6733,"skX":40,"skY":40,"x":-45.5024},"duration":0}],"name":"sss_flah_room_shengli_guang"},{"frame":[{"tweenEasing":0,"transform":{"scX":0.2,"scY":0.2},"duration":5},{"tweenEasing":0,"transform":{"scX":1.95,"scY":1.9},"duration":5},{"tweenEasing":null,"transform":{"scX":3,"scY":3},"duration":80}],"name":"nn_gg2"},{"frame":[{"tweenEasing":0,"transform":{"y":-18.6704,"scX":0.1,"scY":0.1},"duration":3},{"tweenEasing":0,"transform":{"y":-18.6704,"scX":0.5,"scY":0.5},"duration":8},{"tweenEasing":null,"transform":{"y":-18.6704,"scX":2.67,"scY":2.67},"duration":79}],"name":"nn-guang"},{"frame":[{"tweenEasing":null,"transform":{},"duration":2},{"tweenEasing":0,"transform":{"y":-18.6704,"scX":0.1,"scY":0.1},"duration":3},{"tweenEasing":0,"transform":{"y":-18.6704,"scX":0.5,"scY":0.5},"duration":8},{"tweenEasing":null,"transform":{"y":-18.6704,"scX":2.67,"scY":2.67},"duration":77}],"name":"newLayer2"},{"frame":[{"tweenEasing":null,"transform":{},"duration":2},{"tweenEasing":0,"transform":{"y":-16.7871,"scX":0.2,"scY":0.2,"x":180.0952},"duration":5},{"tweenEasing":0,"transform":{"y":-16.7871,"scX":3.95,"scY":3.95,"x":1063.6336},"duration":9},{"tweenEasing":null,"transform":{"y":-16.7871,"scX":5,"scY":5,"x":1469.7195},"duration":74}],"name":"nn_ghgh11"},{"frame":[{"tweenEasing":null,"transform":{},"duration":2},{"tweenEasing":0,"transform":{"y":-10.2459,"scX":-0.2,"scY":0.2,"x":10.8855},"duration":5},{"tweenEasing":0,"transform":{"y":-10.2459,"scX":-3.5,"scY":3.95,"x":-983.2209},"duration":9},{"tweenEasing":null,"transform":{"y":-10.2459,"scX":-5,"scY":5,"x":-1369.2035},"duration":74}],"name":"nn_ghgh111"},{"frame":[{"tweenEasing":null,"transform":{},"duration":90}],"name":"newLayer3"},{"frame":[{"tweenEasing":null,"transform":{},"duration":7},{"tweenEasing":0,"transform":{"y":-353.5759,"scX":0.01,"scY":0.01,"x":155.0586},"duration":24},{"tweenEasing":0,"transform":{"y":-353.5759,"skX":30,"skY":30,"scX":0.6,"scY":0.6,"x":155.0586},"duration":23},{"tweenEasing":null,"transform":{"y":-353.5759,"skX":60,"skY":60,"scX":0.01,"scY":0.01,"x":155.0586},"duration":36}],"name":"BaiRenWin"},{"frame":[{"tweenEasing":null,"transform":{},"duration":13},{"tweenEasing":0,"transform":{"y":-237.65,"scX":0.01,"scY":0.01,"x":-291.26},"duration":24},{"tweenEasing":0,"transform":{"y":-237.6478,"skX":30,"skY":30,"scX":0.6,"scY":0.6,"x":-291.2645},"duration":23},{"tweenEasing":null,"transform":{"y":-237.65,"skX":60,"skY":60,"scX":0.01,"scY":0.01,"x":-291.26},"duration":30}],"name":"newLayer4"},{"frame":[{"tweenEasing":null,"transform":{},"duration":9},{"tweenEasing":0,"transform":{"y":-157.43,"scX":0.01,"scY":0.01,"x":33.43},"duration":24},{"tweenEasing":0,"transform":{"y":-157.4294,"skX":30,"skY":30,"scX":0.6,"scY":0.6,"x":33.429},"duration":23},{"tweenEasing":null,"transform":{"y":-157.43,"skX":60,"skY":60,"scX":0.01,"scY":0.01,"x":33.43},"duration":34}],"name":"newLayer5"},{"frame":[{"tweenEasing":null,"transform":{},"duration":15},{"tweenEasing":0,"transform":{"y":-445.44,"scX":0.01,"scY":0.01,"x":-48.84},"duration":24},{"tweenEasing":0,"transform":{"y":-445.4382,"skX":30,"skY":30,"scX":0.6,"scY":0.6,"x":-48.8424},"duration":23},{"tweenEasing":null,"transform":{"y":-445.44,"skX":60,"skY":60,"scX":0.01,"scY":0.01,"x":-48.84},"duration":28}],"name":"newLayer6"},{"frame":[{"tweenEasing":null,"transform":{},"duration":24},{"tweenEasing":0,"transform":{"y":-256.37,"scX":0.01,"scY":0.01,"x":94.86},"duration":24},{"tweenEasing":0,"transform":{"y":-256.3692,"skX":30,"skY":30,"scX":0.6,"scY":0.6,"x":94.8648},"duration":23},{"tweenEasing":null,"transform":{"y":-256.37,"skX":60,"skY":60,"scX":0.01,"scY":0.01,"x":94.86},"duration":19}],"name":"newLayer7"},{"frame":[{"tweenEasing":null,"transform":{},"duration":8},{"tweenEasing":0,"transform":{"y":-425.7184,"skX":-36.4069,"skY":-36.4069,"x":-233.0757},"duration":3},{"tweenEasing":0,"transform":{"y":-560.5209,"skX":-36.4069,"skY":-36.4069,"x":-342.6028},"duration":7},{"tweenEasing":null,"transform":{"y":-439.8214,"skX":-142.4031,"skY":-142.4031,"x":-470.8116},"duration":72}],"name":"jjh_nn_sl_cd"},{"frame":[{"tweenEasing":null,"transform":{},"duration":8},{"tweenEasing":0,"transform":{"y":-407.8777,"x":-95.0407},"duration":4},{"tweenEasing":0,"transform":{"y":-388.5893,"x":-334.768},"duration":7},{"tweenEasing":0,"transform":{"y":-388.5893,"x":-334.768},"duration":1},{"tweenEasing":null,"transform":{"y":-402.3668,"x":359.6144},"duration":70}],"name":"jjh_nn_sl_cd1"},{"frame":[{"tweenEasing":null,"transform":{},"duration":8},{"tweenEasing":0,"transform":{"y":-407.8777,"x":-95.0407},"duration":4},{"tweenEasing":0,"transform":{"y":-482.1381,"skX":62.2978,"skY":62.2978,"x":-288.0625},"duration":7},{"tweenEasing":null,"transform":{"y":-388.5893,"x":-334.768},"duration":71}],"name":"newLayer8"},{"frame":[{"tweenEasing":null,"transform":{},"duration":10},{"tweenEasing":0,"transform":{"y":-425.7184,"skX":-36.4069,"skY":-36.4069,"scY":-1,"x":171.0163},"duration":3},{"tweenEasing":0,"transform":{"y":-560.5209,"skX":-36.4069,"skY":-36.4069,"scY":-1,"x":296.1188},"duration":7},{"tweenEasing":null,"transform":{"y":-439.8214,"skX":-142.4031,"skY":-142.4031,"scY":-1,"x":496.6394},"duration":70}],"name":"newLayer9"},{"frame":[{"tweenEasing":null,"transform":{},"duration":9},{"tweenEasing":0,"transform":{"y":-402.3668,"x":194.2853},"duration":4},{"tweenEasing":0,"transform":{"y":-435.2948,"skX":62.2978,"skY":62.2978,"x":376.0095},"duration":7},{"tweenEasing":null,"transform":{"y":-388.5893,"x":433.1859},"duration":70}],"name":"newLayer10"},{"frame":[{"tweenEasing":null,"transform":{},"duration":10},{"tweenEasing":0,"transform":{"y":-391.1605,"x":163.9677},"duration":4},{"tweenEasing":0,"transform":{"y":-584.1823,"x":478.0931},"duration":8},{"tweenEasing":null,"transform":{"y":-363.6056,"x":615.8674},"duration":68}],"name":"jjh_nn_sl_cd2"},{"frame":[{"tweenEasing":null,"transform":{},"duration":8},{"tweenEasing":0,"transform":{"y":-432.4928,"x":-276.91},"duration":3},{"tweenEasing":0,"transform":{"y":-589.6932,"x":-450.5056},"duration":9},{"tweenEasing":null,"transform":{"y":-333.2953,"x":-603.1595},"duration":70}],"name":"newLayer11"},{"frame":[{"tweenEasing":null,"transform":{},"duration":8},{"tweenEasing":0,"transform":{"y":-449.157,"x":-155.7398},"duration":4},{"tweenEasing":0,"transform":{"y":-617.2417,"x":-392.7116},"duration":8},{"tweenEasing":null,"transform":{"y":-383.0254,"skX":-49.6355,"skY":-49.6355,"x":-555.2852},"duration":70}],"name":"jjh_nn_sl_cd3"},{"frame":[{"tweenEasing":null,"transform":{},"duration":9},{"tweenEasing":0,"transform":{"y":-457.4235,"scX":-1,"x":125.3197},"duration":4},{"tweenEasing":0,"transform":{"y":-562.1319,"scX":-1,"x":433.9342},"duration":8},{"tweenEasing":null,"transform":{"y":-383.0254,"skX":-49.6355,"skY":-49.6355,"scX":-1,"x":585.4859},"duration":69}],"name":"newLayer12"},{"frame":[{"tweenEasing":null,"transform":{},"duration":9},{"tweenEasing":0,"transform":{"y":-399.4871,"skX":-43.5361,"skY":-43.5361,"x":95.1699},"duration":5},{"tweenEasing":0,"transform":{"y":-611.6595,"x":417.424},"duration":8},{"tweenEasing":null,"transform":{"y":-413.2646,"skX":46.3168,"skY":46.3168,"x":516.7592},"duration":68}],"name":"jjh_nn_sl_cd4"},{"frame":[{"tweenEasing":null,"transform":{},"duration":9},{"tweenEasing":0,"transform":{"y":-443.5749,"scX":-1,"x":-161.228},"duration":6},{"tweenEasing":0,"transform":{"y":-583.9669,"skX":32.7741,"skY":32.7741,"scX":-1,"x":-387.1779},"duration":8},{"tweenEasing":null,"transform":{"y":-396.7316,"skX":-44.2171,"skY":-44.2171,"scX":-1,"x":-588.3283},"duration":67}],"name":"jjh_nn_sl_cd41"}]}],"frameRate":24,"defaultActions":[{"gotoAndPlay":"nn_mlzpan"}],"bone":[{"name":"root","transform":{}},{"transform":{},"name":"nn_gg7","parent":"root"},{"transform":{},"name":"nn_gg1","parent":"root"},{"transform":{},"name":"nn_gg71","parent":"root"},{"transform":{},"name":"nn_pmd","parent":"root"},{"transform":{},"name":"nn-zhou","parent":"root"},{"transform":{},"name":"nn-zhou1","parent":"root"},{"transform":{},"name":"newLayer","parent":"root"},{"transform":{},"name":"newLayer1","parent":"root"},{"transform":{},"name":"nn-走灯","parent":"root"},{"transform":{},"name":"nn-指针","parent":"root"},{"transform":{},"name":"未标题-2","parent":"root"},{"transform":{},"name":"sss_flah_room_shengli_guang","parent":"root"},{"transform":{},"name":"nn_gg2","parent":"root"},{"transform":{},"name":"nn-guang","parent":"root"},{"transform":{},"name":"newLayer2","parent":"root"},{"transform":{},"name":"nn_ghgh11","parent":"root"},{"transform":{},"name":"nn_ghgh111","parent":"root"},{"transform":{},"name":"newLayer3","parent":"root"},{"transform":{},"name":"BaiRenWin","parent":"root"},{"transform":{},"name":"newLayer4","parent":"root"},{"transform":{},"name":"newLayer5","parent":"root"},{"transform":{},"name":"newLayer6","parent":"root"},{"transform":{},"name":"newLayer7","parent":"root"},{"transform":{},"name":"jjh_nn_sl_cd","parent":"root"},{"transform":{},"name":"jjh_nn_sl_cd1","parent":"root"},{"transform":{},"name":"newLayer8","parent":"root"},{"transform":{},"name":"newLayer9","parent":"root"},{"transform":{},"name":"newLayer10","parent":"root"},{"transform":{},"name":"jjh_nn_sl_cd2","parent":"root"},{"transform":{},"name":"newLayer11","parent":"root"},{"transform":{},"name":"jjh_nn_sl_cd3","parent":"root"},{"transform":{},"name":"newLayer12","parent":"root"},{"transform":{},"name":"jjh_nn_sl_cd4","parent":"root"},{"transform":{},"name":"jjh_nn_sl_cd41","parent":"root"}]}],"frameRate":24,"name":"nn_mlcjiang","version":"4.5","isGlobal":0}